LICENSE
README.md
setup.py
graphembed/_version.py
graphembed/display.py
graphembed/graph_embed.py
graphembed/graph_layout_embedder.py
graphembed.egg-info/PKG-INFO
graphembed.egg-info/SOURCES.txt
graphembed.egg-info/dependency_links.txt
graphembed.egg-info/entry_points.txt
graphembed.egg-info/requires.txt
graphembed.egg-info/top_level.txt