Metadata-Version: 2.1
Name: graphembed
Version: 0.0.112
Summary: 2D embedding of a data matrix given supervised class information
Home-page: https://github.com/smautner/
Author: Stefan Mautner
Author-email: myl4stn4m3@cs.uni-freiburg.de
License: LICENSE
License-File: LICENSE
